COPYING
MANIFEST.in
README.rst
__init__.py
setup.py
canossa/__init__.py
canossa/attribute.py
canossa/canossa.py
canossa/cell.py
canossa/constant.py
canossa/cursor.py
canossa/exception.py
canossa/iframe.py
canossa/interface.py
canossa/line.py
canossa/mouse.py
canossa/output.py
canossa/popup.py
canossa/screen.py
canossa/stub.py
canossa.egg-info/PKG-INFO
canossa.egg-info/SOURCES.txt
canossa.egg-info/dependency_links.txt
canossa.egg-info/eager_resources.txt
canossa.egg-info/entry_points.txt
canossa.egg-info/requires.txt
canossa.egg-info/top_level.txt
canossa.egg-info/zip-safe
canossa/termprop/__init__.py
canossa/termprop/setup.py
canossa/termprop/termprop/__init__.py
canossa/termprop/termprop/termprop.py
canossa/termprop/termprop/wcwidth.py
canossa/termprop/termprop/db/__init__.py
canossa/termprop/termprop/db/iterm2/__init__.py
canossa/termprop/termprop/db/unicode6_2/__init__.py
canossa/termprop/termprop/db/unicode6_2/cjk.py
canossa/termprop/termprop/db/unicode6_2/normal.py
canossa/tff/__init__.py
canossa/tff/setup.py
canossa/tff/tff.py